simpervisor/__init__.py
simpervisor/atexitasync.py
simpervisor/process.py
simpervisor-0.4.dist-info/LICENSE
simpervisor-0.4.dist-info/METADATA
simpervisor-0.4.dist-info/WHEEL
simpervisor-0.4.dist-info/top_level.txt
simpervisor-0.4.dist-info/RECORD
